librelane/design/zdb_top/controller_locked.sv
/*
Module      : dll_controller_acquire_track
Author      : Mythri Muralikannan
Description : Acquire/track DLL controller

Function:
Uses two operating modes:
- Acquire mode for fast lock
- Track mode for fine steady-state adjustment
*/


`timescale 1ps/1ps

module controller #(
    parameter integer CTRL_BITS        = 6,
    parameter integer INIT_CTRL        = 32,
    parameter integer ACQUIRE_STEP     = 4,
    parameter integer TRACK_STEP       = 1,
    parameter integer QUIET_CYCLES     = 8
)(
    input  wire                 clk_in,
    input  wire                 rst,
    input  wire                 up,
    input  wire                 down,
    output reg  [CTRL_BITS-1:0] ctrl
);

    localparam integer MAX_CTRL = (1 << CTRL_BITS) - 1;
    localparam [CTRL_BITS-1:0] ZERO_CTRL = {CTRL_BITS{1'b0}};
    localparam [CTRL_BITS-1:0] MAX_CTRL_VEC = MAX_CTRL[CTRL_BITS-1:0];

    localparam ACQUIRE = 1'b0;
    localparam TRACK   = 1'b1;

    reg mode;
    reg [$clog2(QUIET_CYCLES + 1)-1:0] quiet_count;

    integer step_size;
    integer next_ctrl;

    always @(posedge clk_in or posedge rst) begin
        if (rst) begin
            mode       <= ACQUIRE;
            quiet_count <= 0;

            if (INIT_CTRL < 0)
                ctrl <= ZERO_CTRL;
            else if (INIT_CTRL > MAX_CTRL)
                ctrl <= MAX_CTRL_VEC;
            else
                ctrl <= INIT_CTRL[CTRL_BITS-1:0];
        end else begin
            step_size = (mode == ACQUIRE) ? ACQUIRE_STEP : TRACK_STEP;

            case ({up, down})
                2'b10: begin
                    quiet_count <= 0;
                    next_ctrl   = ctrl + step_size;
                    if (next_ctrl > MAX_CTRL)
                        ctrl <= MAX_CTRL_VEC;
                    else
                        ctrl <= next_ctrl[CTRL_BITS-1:0];
                end

                2'b01: begin
                    quiet_count <= 0;
                    next_ctrl   = ctrl - step_size;
                    if (next_ctrl < 0)
                        ctrl <= ZERO_CTRL;
                    else
                        ctrl <= next_ctrl[CTRL_BITS-1:0];
                end

                default: begin
                    ctrl <= ctrl;
                    if (quiet_count < QUIET_CYCLES)
                        quiet_count <= quiet_count + 1'b1;
                end
            endcase

            if (quiet_count == QUIET_CYCLES - 1)
                mode <= TRACK;
        end
    end

endmodule

waveform_viz/testbenches/tb_controller_viz.sv
`timescale 1ps/1ps

module tb_controller_viz;

    parameter integer CTRL_BITS = 6;
    parameter integer INIT_CTRL = 32;

    reg clk_in, rst, up, down;
    wire [CTRL_BITS-1:0] ctrl;

    controller #(
        .CTRL_BITS(CTRL_BITS),
        .INIT_CTRL(INIT_CTRL)
    ) dut (
        .clk_in(clk_in), .rst(rst), .up(up), .down(down), .ctrl(ctrl)
    );

    initial clk_in = 1'b0;
    always #5000 clk_in = ~clk_in;

    reg [8*512-1:0] fsdbpath;

    initial begin
        if (!$value$plusargs("fsdbpath=%s", fsdbpath)) fsdbpath = "dump.fsdb";

        $fsdbDumpfile(fsdbpath);
        $fsdbDumpvars(0, dut);

        // Reset
        rst = 1; up = 0; down = 0;
        repeat (2) @(posedge clk_in);
        rst = 0;
        @(posedge clk_in);

        // Demo: ramp up, hold, ramp down — shows typical controller behavior
        up = 1; down = 0;
        repeat (40) @(posedge clk_in);

        up = 0; down = 0;
        repeat (8) @(posedge clk_in);

        up = 0; down = 1;
        repeat (40) @(posedge clk_in);

        up = 0; down = 0;
        repeat (4) @(posedge clk_in);

        $finish;
    end

endmodule

waveform_viz/vcd/controller.vcd
$date
	Fri Mar 27 17:02:50 2026

$end
$version
	Chronologic Simulation VCS Release X-2025.06-SP2_Full64
$end
$timescale
	1ps
$end
$scope module tb_controller_viz $end
$scope module dut $end
$var wire 1 ! clk_in $end
$var wire 1 " rst $end
$var wire 1 # up $end
$var wire 1 $ down $end
$var reg 6 % ctrl [5:0] $end
$upscope $end
$upscope $end
$enddefinitions $end
$dumpvars
0!
b100000 %
1"
0$
0#
$end
#5000
1!
#10000
0!
#15000
0"
1!
#20000
0!
#25000
b100001 %
1!
1#
#30000
0!
#35000
b100010 %
1!
#40000
0!
#45000
b100011 %
1!
#50000
0!
#55000
b100100 %
1!
#60000
0!
#65000
b100101 %
1!
#70000
0!
#75000
b100110 %
1!
#80000
0!
#85000
b100111 %
1!
#90000
0!
#95000
b101000 %
1!
#100000
0!
#105000
b101001 %
1!
#110000
0!
#115000
b101010 %
1!
#120000
0!
#125000
b101011 %
1!
#130000
0!
#135000
b101100 %
1!
#140000
0!
#145000
b101101 %
1!
#150000
0!
#155000
b101110 %
1!
#160000
0!
#165000
b101111 %
1!
#170000
0!
#175000
b110000 %
1!
#180000
0!
#185000
b110001 %
1!
#190000
0!
#195000
b110010 %
1!
#200000
0!
#205000
b110011 %
1!
#210000
0!
#215000
b110100 %
1!
#220000
0!
#225000
b110101 %
1!
#230000
0!
#235000
b110110 %
1!
#240000
0!
#245000
b110111 %
1!
#250000
0!
#255000
b111000 %
1!
#260000
0!
#265000
b111001 %
1!
#270000
0!
#275000
b111010 %
1!
#280000
0!
#285000
b111011 %
1!
#290000
0!
#295000
b111100 %
1!
#300000
0!
#305000
b111101 %
1!
#310000
0!
#315000
b111110 %
1!
#320000
0!
#325000
b111111 %
1!
#330000
0!
#335000
1!
#340000
0!
#345000
1!
#350000
0!
#355000
1!
#360000
0!
#365000
1!
#370000
0!
#375000
1!
#380000
0!
#385000
1!
#390000
0!
#395000
1!
#400000
0!
#405000
1!
#410000
0!
#415000
1!
#420000
0!
#425000
0#
1!
#430000
0!
#435000
1!
#440000
0!
#445000
1!
#450000
0!
#455000
1!
#460000
0!
#465000
1!
#470000
0!
#475000
1!
#480000
0!
#485000
1!
#490000
0!
#495000
1!
#500000
0!
#505000
1$
1!
b111110 %
#510000
0!
#515000
b111101 %
1!
#520000
0!
#525000
b111100 %
1!
#530000
0!
#535000
b111011 %
1!
#540000
0!
#545000
b111010 %
1!
#550000
0!
#555000
b111001 %
1!
#560000
0!
#565000
b111000 %
1!
#570000
0!
#575000
b110111 %
1!
#580000
0!
#585000
b110110 %
1!
#590000
0!
#595000
b110101 %
1!
#600000
0!
#605000
b110100 %
1!
#610000
0!
#615000
b110011 %
1!
#620000
0!
#625000
b110010 %
1!
#630000
0!
#635000
b110001 %
1!
#640000
0!
#645000
b110000 %
1!
#650000
0!
#655000
b101111 %
1!
#660000
0!
#665000
b101110 %
1!
#670000
0!
#675000
b101101 %
1!
#680000
0!
#685000
b101100 %
1!
#690000
0!
#695000
b101011 %
1!
#700000
0!
#705000
b101010 %
1!
#710000
0!
#715000
b101001 %
1!
#720000
0!
#725000
b101000 %
1!
#730000
0!
#735000
b100111 %
1!
#740000
0!
#745000
b100110 %
1!
#750000
0!
#755000
b100101 %
1!
#760000
0!
#765000
b100100 %
1!
#770000
0!
#775000
b100011 %
1!
#780000
0!
#785000
b100010 %
1!
#790000
0!
#795000
b100001 %
1!
#800000
0!
#805000
b100000 %
1!
#810000
0!
#815000
b011111 %
1!
#820000
0!
#825000
b011110 %
1!
#830000
0!
#835000
b011101 %
1!
#840000
0!
#845000
b011100 %
1!
#850000
0!
#855000
b011011 %
1!
#860000
0!
#865000
b011010 %
1!
#870000
0!
#875000
b011001 %
1!
#880000
0!
#885000
b011000 %
1!
#890000
0!
#895000
b010111 %
1!
#900000
0!
#905000
0$
1!
