librelane/design/zdb_top/phase_detector_syn_pfd.sv
`timescale 1ps/1ps

/*
Module      : phase_frequency_detector
Author      : Mythri Muralikannan
Description : Two-flip-flop phase-frequency detector (PFD)

Function:
Compares the rising edges of the reference clock (clk_in) and the
feedback clock (clk_out) and generates UP/DOWN control signals.

Output meaning:
up = 1 -> reference clock leads feedback clock -> speed up loop
down = 1 -> feedback clock leads reference clock -> slow down loop
*/

module phase_detector (
    input  wire clk_in,     // Reference clock
    input  wire clk_out,    // Feedback clock
    input  wire rst,        // Asynchronous active-high reset
    output wire up,         // Request to speed up
    output wire down        // Request to slow down
);

    reg up_ff;
    reg down_ff;

    // Internal reset: clears both flip-flops when both outputs are high
    wire clr;
    assign clr = rst | (up_ff & down_ff);

    // Set UP on reference clock edge
    always @(posedge clk_in or posedge rst) begin
        if (rst)
            up_ff <= 1'b0;
        else if (clr)
            up_ff <= 1'b0;
        else
            up_ff <= 1'b1;
    end

    // Set DOWN on feedback clock edge
    always @(posedge clk_out or posedge rst) begin
        if (rst)
            down_ff <= 1'b0;
        else if (clr)
            down_ff <= 1'b0;
        else
            down_ff <= 1'b1;
    end

    // Output assignments
    assign up   = up_ff;
    assign down = down_ff;

endmodule

waveform_viz/testbenches/tb_phase_detector_viz.sv
`timescale 1ps/1ps

module tb_phase_detector_viz;

    reg  clk_in, clk_out, rst;
    wire up, down;

    phase_detector dut (
        .clk_in(clk_in), .clk_out(clk_out), .rst(rst),
        .up(up), .down(down)
    );

    reg [8*512-1:0] fsdbpath;

    initial begin
        if (!$value$plusargs("fsdbpath=%s", fsdbpath)) fsdbpath = "dump.fsdb";

        $fsdbDumpfile(fsdbpath);
        $fsdbDumpvars(0, dut);

        clk_in = 0; clk_out = 0; rst = 1;
        #10000; rst = 0; #5000;

        // Demo: clk_out lags clk_in by 2ns — typical PD usage showing UP dominance
        begin : lag_demo
            integer ii, half, phase;
            half = 5000;   // 10ns period
            phase = 2000;  // 2ns lag
            for (ii = 0; ii < 16; ii = ii + 1) begin
                clk_in = 1; #(phase); clk_out = 1; #(half - phase);
                clk_in = 0; #(phase); clk_out = 0; #(half - phase);
            end
        end

        clk_in = 0; clk_out = 0; #5000;
        $finish;
    end

endmodule

waveform_viz/vcd/phase_detector.vcd
$date
	Fri Mar 27 17:02:55 2026

$end
$version
	Chronologic Simulation VCS Release X-2025.06-SP2_Full64
$end
$timescale
	1ps
$end
$scope module tb_phase_detector_viz $end
$scope module dut $end
$var wire 1 ! clk_in $end
$var wire 1 " clk_out $end
$var wire 1 # rst $end
$var wire 1 % up $end
$var wire 1 ' down $end
$var reg 1 ( up_ff $end
$var reg 1 ) down_ff $end
$var wire 1 * clr $end
$upscope $end
$upscope $end
$enddefinitions $end
$dumpvars
0!
1*
0"
0%
0'
1#
0)
0(
$end
#10000
0*
0#
#15000
1!
1%
1(
#17000
0%
0(
1"
#20000
0!
#22000
0"
#25000
1!
1%
1(
#27000
0%
0(
1"
#30000
0!
#32000
0"
#35000
1!
1%
1(
#37000
0%
0(
1"
#40000
0!
#42000
0"
#45000
1!
1%
1(
#47000
0%
0(
1"
#50000
0!
#52000
0"
#55000
1!
1%
1(
#57000
0%
0(
1"
#60000
0!
#62000
0"
#65000
1!
1%
1(
#67000
0%
0(
1"
#70000
0!
#72000
0"
#75000
1!
1%
1(
#77000
0%
0(
1"
#80000
0!
#82000
0"
#85000
1!
1%
1(
#87000
0%
0(
1"
#90000
0!
#92000
0"
#95000
1!
1%
1(
#97000
0%
0(
1"
#100000
0!
#102000
0"
#105000
1!
1%
1(
#107000
0%
0(
1"
#110000
0!
#112000
0"
#115000
1!
1%
1(
#117000
0%
0(
1"
#120000
0!
#122000
0"
#125000
1!
1%
1(
#127000
0%
0(
1"
#130000
0!
#132000
0"
#135000
1!
1%
1(
#137000
0%
0(
1"
#140000
0!
#142000
0"
#145000
1!
1%
1(
#147000
0%
0(
1"
#150000
0!
#152000
0"
#155000
1!
1%
1(
#157000
0%
0(
1"
#160000
0!
#162000
0"
#165000
1!
1%
1(
#167000
0%
0(
1"
